exchange_sdk/__init__.py
exchange_sdk/client.py
exchange_sdk-1.0.0.dist-info/METADATA
exchange_sdk-1.0.0.dist-info/WHEEL
exchange_sdk-1.0.0.dist-info/top_level.txt
exchange_sdk-1.0.0.dist-info/RECORD
