Metadata-Version: 2.4
Name: exchange-sdk
Version: 1.0.0
Summary: Python SDK for high-frequency trading competition platform
Author-email: Your Name <your.email@example.com>
License: MIT
Project-URL: Homepage, https://github.com/Ngafney/Exchange
Project-URL: Repository, https://github.com/Ngafney/Exchange
Project-URL: Documentation, https://github.com/Ngafney/Exchange/tree/main/services/sdk_python
Keywords: trading,exchange,hft,competition
Classifier: Development Status :: 3 - Alpha
Classifier: Intended Audience :: Education
Classifier: License :: OSI Approved :: MIT License
Classifier: Programming Language :: Python :: 3
Classifier: Programming Language :: Python :: 3.11
Classifier: Programming Language :: Python :: 3.12
Requires-Python: >=3.11
